pagesj2/__init__.py
pagesj2/plugin.py
mkdocs_pages_j2_plugin-0.3.1.dist-info/METADATA
mkdocs_pages_j2_plugin-0.3.1.dist-info/WHEEL
mkdocs_pages_j2_plugin-0.3.1.dist-info/entry_points.txt
mkdocs_pages_j2_plugin-0.3.1.dist-info/RECORD
